kit/__init__.py
kit/decorators.py
kit/hydra/__init__.py
kit/hydra/relay.py
kit/hydra/utils.py
kit/logging.py
kit/misc.py
kit/pl/__init__.py
kit/pl/utils.py
kit/py.typed
kit/torch/__init__.py
kit/torch/data.py
kit/torch/loss.py
kit/torch/transforms/__init__.py
kit/torch/transforms/mixup.py
kit/torch/utils.py
kit/wandb.py
palkit-0.4.2.dist-info/LICENSE
palkit-0.4.2.dist-info/WHEEL
palkit-0.4.2.dist-info/METADATA
palkit-0.4.2.dist-info/RECORD
